alumath_matrix/__init__.py
alumath_matrix/matrix_ops.py
alumath_matrix-0.1.0.dist-info/licenses/LICENSE
alumath_matrix-0.1.0.dist-info/METADATA
alumath_matrix-0.1.0.dist-info/WHEEL
alumath_matrix-0.1.0.dist-info/top_level.txt
alumath_matrix-0.1.0.dist-info/RECORD
