Metadata-Version: 2.4
Name: alumath_matrix
Version: 0.1.0
Summary: A simple matrix multiplication library
Home-page: https://github.com/Stecie06/alumath_matrix
Author: Stecie Niyonzima
Author-email: n.stecie@alustudent.com
Classifier: Programming Language :: Python :: 3
Classifier: License :: OSI Approved :: MIT License
Classifier: Operating System :: OS Independent
Requires-Python: >=3.6
License-File: LICENSE
Dynamic: author
Dynamic: author-email
Dynamic: classifier
Dynamic: description
Dynamic: description-content-type
Dynamic: home-page
Dynamic: license-file
Dynamic: requires-python
Dynamic: summary
